setup.py
legos/__init__.py
legos/cryptocurrency.py
legos/stocks.py
legos.stocks.egg-info/PKG-INFO
legos.stocks.egg-info/SOURCES.txt
legos.stocks.egg-info/dependency_links.txt
legos.stocks.egg-info/namespace_packages.txt
legos.stocks.egg-info/requires.txt
legos.stocks.egg-info/top_level.txt