Metadata-Version: 1.1
Name: legos.stocks
Version: 0.1.5
Summary: A legobot plugin for checking stocks and cryptocurrency prices
Home-page: https://github.com/bbriggs/legos.stocks
Author: Brenton Briggs II
Author-email: UNKNOWN
License: GPLv3
Platform: UNKNOWN
Classifier: License :: OSI Approved :: GNU General Public License v3 (GPLv3)
Classifier: Development Status :: 4 - Beta
Classifier: Programming Language :: Python :: 3
